programmingwithkumaresan/__init__.py
programmingwithkumaresan/main.py
subtranslator-0.0.2.dist-info/METADATA
subtranslator-0.0.2.dist-info/WHEEL
subtranslator-0.0.2.dist-info/top_level.txt
subtranslator-0.0.2.dist-info/RECORD
