Metadata-Version: 2.1
Name: subtranslator
Version: 0.0.2
Requires-Dist: pysrt
Requires-Dist: translate
